.travis.yml
AUTHORS.rst
CONTRIBUTING.rst
HISTORY.rst
LICENSE
MANIFEST.in
Makefile
README.rst
requirements.txt
setup.cfg
setup.py
topdf.sh
tox.ini
docs/Makefile
docs/authors.rst
docs/conf.py
docs/contributing.rst
docs/history.rst
docs/iconframer.yaml
docs/index.rst
docs/installation.rst
docs/make.bat
docs/readme.rst
docs/usage.rst
iconframer/__init__.py
iconframer/cli.py
iconframer/iconframer.py
iconframer.egg-info/PKG-INFO
iconframer.egg-info/SOURCES.txt
iconframer.egg-info/dependency_links.txt
iconframer.egg-info/entry_points.txt
iconframer.egg-info/not-zip-safe
iconframer.egg-info/requires.txt
iconframer.egg-info/top_level.txt
tests/.DS_Store
tests/__init__.py
tests/test_iconframer.py