Metadata-Version: 1.1
Name: iconframer
Version: 0.3
Summary: Generate framed and labelled SVG icons
Home-page: https://github.com/koodaamo/iconframer
Author: Petri Savolainen
Author-email: petri.savolainen@koodaamo.fi
License: BSD
Keywords: iconframer
Platform: UNKNOWN
Classifier: Development Status :: 4 - Beta
Classifier: Intended Audience :: Developers
Classifier: License :: OSI Approved :: GNU Affero General Public License v3 or later (AGPLv3+)
Classifier: Natural Language :: English
Classifier: Programming Language :: Python :: 2
Classifier: Programming Language :: Python :: 2.6
Classifier: Programming Language :: Python :: 2.7
Classifier: Programming Language :: Python :: 3
Classifier: Programming Language :: Python :: 3.3
Classifier: Programming Language :: Python :: 3.4
